{
  "delta-count": {
    "background-color": {
      "value": "$semantic.color.surface.default",
      "type": "color"
    },
    "border-color": {
      "value": "$semantic.color.border.neutral.default",
      "type": "color"
    },
    "removed": {
      "text-color": {
        "value": "$semantic.color.text.danger",
        "type": "color"
      },
      "icon-color": {
        "value": "$semantic.color.icon.danger",
        "type": "color"
      }
    },
    "changed": {
      "text-color": {
        "value": "$semantic.color.text.warning",
        "type": "color"
      },
      "icon-color": {
        "value": "$semantic.color.icon.warning",
        "type": "color"
      }
    },
    "unchanged": {
      "text-color": {
        "value": "$semantic.color.text.weaker",
        "type": "color"
      },
      "icon-color": {
        "value": "$semantic.color.icon.weaker",
        "type": "color"
      }
    },
    "counter-add": {
      "text-color": {
        "value": "$semantic.color.text.success",
        "type": "color"
      },
      "icon-color": {
        "value": "$semantic.color.icon.success",
        "type": "color"
      }
    }
  },
  "deltaCount": {
    "border-width": {
      "value": "$semantic.border-width.default",
      "type": "borderWidth"
    },
    "font": {
      "value": "{typography.n.h6}",
      "type": "typography"
    }
  }
}